todolistz/__init__.py
todolistz/database.py
todolistz/log.py
todolistz/models.py
todolistz/schemas.py
todolistz/server.py
todolistz/toolkit.py
todolistz/api/goals.py
todolistz/api/tasks.py
todolistz/core/broker.py
todolistz/core/executor.py
todolistz/core/miner.py
todolistz-0.1.2.dist-info/METADATA
todolistz-0.1.2.dist-info/WHEEL
todolistz-0.1.2.dist-info/top_level.txt
todolistz-0.1.2.dist-info/RECORD
