Metadata-Version: 2.4
Name: todolistz
Version: 0.1.2
Summary: Add your description here
Requires-Python: >=3.12
Requires-Dist: agno>=2.3.8
Requires-Dist: anyio>=4.12.0
Requires-Dist: colorlog>=6.10.1
Requires-Dist: dotenv>=0.9.9
Requires-Dist: fastapi>=0.123.7
Requires-Dist: openai>=2.9.0
Requires-Dist: psycopg>=3.3.2
Requires-Dist: psycopg2-binary>=2.9.11
Requires-Dist: pymysql>=1.1.2
Requires-Dist: pytest>=9.0.1
Requires-Dist: pytest-asyncio>=1.3.0
Requires-Dist: pytest-tornasync>=0.6.0.post2
Requires-Dist: redis>=7.1.0
Requires-Dist: requests>=2.32.5
Requires-Dist: sqlalchemy>=2.0.44
Requires-Dist: sqlalchemy-utils>=0.42.0
Requires-Dist: toml>=0.10.2
Requires-Dist: uvicorn>=0.38.0
Requires-Dist: websockets>=15.0.1
